{
    "@context": {
        "@base": "http://lynx-project.eu/kos/",
        "dcterms": "http://purl.org/dc/terms/",
        "rdfs": "http://www.w3.org/2000/01/rdf-schema#",
        "rdf": "http://www.w3.org/1999/02/22-rdf-syntax-ns#",
        "dc": "http://purl.org/dc/elements/1.1/",
        "skos": "http://www.w3.org/2004/02/skos/core#",
        "owl": "http://www.w3.org/2002/07/owl#",
        "skos:broader": {
            "@type": "@id"
        },
        "skos:inScheme": {
            "@type": "@id"
        },
        "skos:related": {
            "@type": "@id"
        },
        "skos:narrower": {
            "@type": "@id"
        },
        "skos:hasTopConcept": {
            "@type": "@id"
        },
        "skos:topConceptOf": {
            "@type": "@id"
        }
    },
    "@id": "LT7109906",
    "@type": "skos:Concept",
    "skos:inScheme": "amt",
    "owl:sameAs": "https://iate.europa.eu/entry/result/1394527",
    "skos:topConceptOf": "LT7109906",
    "skos:prefLabel": [
        {
            "@language": "de",
            "@value": "amt"
        }
    ],
    "skos:altLabel": [
        {
            "@language": "de",
            "@value": "Dienstgesch채fte"
        },
        {
            "@language": "de",
            "@value": "Amtsgesch채fte"
        },
        {
            "@language": "de",
            "@value": "Funktion"
        },
        {
            "@language": "de",
            "@value": "dienstliche T채tigkeit"
        },
        {
            "@language": "de",
            "@value": "Amtst채tigkeit"
        },
        {
            "@language": "de",
            "@value": "Dienst"
        },
        {
            "@language": "de",
            "@value": "dienstliche Obliegenheiten"
        },
        {
            "@language": "de",
            "@value": ""
        }
    ],
    "skos:definition": [],
    "skos:broader": [
        "LT2252929"
    ],
    "skos:related": [
        "LT1343020"
    ]
}