{
    "@context": {
        "@base": "http://lynx-project.eu/kos/",
        "dcterms": "http://purl.org/dc/terms/",
        "rdfs": "http://www.w3.org/2000/01/rdf-schema#",
        "rdf": "http://www.w3.org/1999/02/22-rdf-syntax-ns#",
        "dc": "http://purl.org/dc/elements/1.1/",
        "skos": "http://www.w3.org/2004/02/skos/core#",
        "owl": "http://www.w3.org/2002/07/owl#",
        "skos:broader": {
            "@type": "@id"
        },
        "skos:inScheme": {
            "@type": "@id"
        },
        "skos:related": {
            "@type": "@id"
        },
        "skos:narrower": {
            "@type": "@id"
        },
        "skos:hasTopConcept": {
            "@type": "@id"
        },
        "skos:topConceptOf": {
            "@type": "@id"
        }
    },
    "@id": "LT8636332",
    "@type": "skos:Concept",
    "skos:inScheme": "datio in solutum",
    "owl:sameAs": "https://iate.europa.eu/entry/result/1131420",
    "skos:topConceptOf": "LT8636332",
    "skos:prefLabel": [
        {
            "@language": "es",
            "@value": "dación en pago"
        },
        {
            "@language": "en",
            "@value": "datio in solutum"
        },
        {
            "@language": "de",
            "@value": "datio in solutum"
        },
        {
            "@language": "nl",
            "@value": "inbetalinggeving"
        }
    ],
    "skos:altLabel": [
        {
            "@language": "en",
            "@value": "giving in payment"
        },
        {
            "@language": "en",
            "@value": "payment in kind"
        },
        {
            "@language": "de",
            "@value": "Hingabe an Erfüllungs Statt"
        },
        {
            "@language": "nl",
            "@value": "datio in solutum"
        },
        {
            "@language": "de",
            "@value": ""
        }
    ],
    "skos:definition": [
        {
            "@language": "es",
            "@value": "De manera genérica acto en virtud del cual el deudor realiza a título de pago una prestación diversa de la debida al acreedor quien acepta recibirla en sustitución de esta. \nA veces en un sentido más restringido por dación en pago se entiende concretamente la entrega de una cosa corporal o dinero como equivalencia del cumplimiento de la obligación originaria de dar hacer o no hacer. \nLa dación en pago suele aplicarse como sistema de pago final por parte del deudor de una hipoteca inmobiliaria (en caso de que este no pueda hacer frente al pago de las cuotas impuestas por el crédito hipotecario establecido) mediante la entrega del inmueble en vez de dinero para liberarse de la deuda."
        },
        {
            "@language": "en",
            "@value": "act of discharging a debt by giving something instead of paying in money"
        },
        {
            "@language": "nl",
            "@value": "\"handeling waarbij een schuldenaar ter vereffening van zijn schuld aan de schuldeiser met diens instemming een ander goed in betaling geeft dan oorspronkelijk verschuldigd was\""
        }
    ]
}