{
    "@context": {
        "@base": "http://lynx-project.eu/kos/",
        "dcterms": "http://purl.org/dc/terms/",
        "rdfs": "http://www.w3.org/2000/01/rdf-schema#",
        "rdf": "http://www.w3.org/1999/02/22-rdf-syntax-ns#",
        "dc": "http://purl.org/dc/elements/1.1/",
        "skos": "http://www.w3.org/2004/02/skos/core#",
        "owl": "http://www.w3.org/2002/07/owl#",
        "skos:broader": {
            "@type": "@id"
        },
        "skos:inScheme": {
            "@type": "@id"
        },
        "skos:related": {
            "@type": "@id"
        },
        "skos:narrower": {
            "@type": "@id"
        },
        "skos:hasTopConcept": {
            "@type": "@id"
        },
        "skos:topConceptOf": {
            "@type": "@id"
        }
    },
    "@id": "LT7840013",
    "@type": "skos:Concept",
    "skos:inScheme": "gewinn, entgangener",
    "owl:sameAs": "https://iate.europa.eu/entry/result/1395563",
    "skos:topConceptOf": "LT7840013",
    "skos:prefLabel": [
        {
            "@language": "es",
            "@value": "lucro cesante"
        },
        {
            "@language": "de",
            "@value": "gewinn, entgangener"
        },
        {
            "@language": "es",
            "@value": "lucro cesante"
        },
        {
            "@language": "en",
            "@value": "loss of profits"
        },
        {
            "@language": "de",
            "@value": "gewinn, entgangener"
        },
        {
            "@language": "nl",
            "@value": "winstderving"
        },
        {
            "@language": "de",
            "@value": "gewinn, entgangener"
        },
        {
            "@language": "es",
            "@value": "beneficio perdido"
        },
        {
            "@language": "en",
            "@value": "lost profit"
        },
        {
            "@language": "de",
            "@value": "gewinn, entgangener"
        },
        {
            "@language": "nl",
            "@value": "gederfde winst"
        }
    ],
    "skos:altLabel": [
        {
            "@language": "es",
            "@value": "negocio fallido"
        },
        {
            "@language": "es",
            "@value": "ganancia fallida"
        },
        {
            "@language": "es",
            "@value": "beneficio fallido"
        },
        {
            "@language": "de",
            "@value": "Verdienstentgang"
        },
        {
            "@language": "de",
            "@value": "Lohnausfall"
        },
        {
            "@language": "de",
            "@value": "Verdienstverlust"
        },
        {
            "@language": "de",
            "@value": "entgangener Gewinn"
        },
        {
            "@language": "en",
            "@value": "lost profits"
        },
        {
            "@language": "de",
            "@value": "Gewinnausfall"
        },
        {
            "@language": "de",
            "@value": "Verlust an Einnahmen"
        },
        {
            "@language": "de",
            "@value": "entgangener Gewinn"
        },
        {
            "@language": "es",
            "@value": "lucro cesante"
        },
        {
            "@language": "de",
            "@value": ""
        }
    ],
    "skos:definition": [
        {
            "@language": "es",
            "@value": "\"Ganancia o beneficio que se ha dejado de obtener a consecuencia de la actuación de un tercero. Beneficio o utilidad que se habría conseguido de haber empleado directamente un capital durante el tiempo que ha estado destinado a un préstamo empréstito o mutuo. (...) El lucro cesante es la base para el pago de los intereses.\" (Diccionario de Finanzas y Banca)"
        },
        {
            "@language": "de",
            "@value": "entgangener Gewinn liegt dann vor wenn der Eintritt einer Vermögensvermehrung verhindet also eine Erwerbschance vernichtet wird."
        }
    ]
}