{
    "@context": {
        "@base": "http://lynx-project.eu/kos/",
        "dcterms": "http://purl.org/dc/terms/",
        "rdfs": "http://www.w3.org/2000/01/rdf-schema#",
        "rdf": "http://www.w3.org/1999/02/22-rdf-syntax-ns#",
        "dc": "http://purl.org/dc/elements/1.1/",
        "skos": "http://www.w3.org/2004/02/skos/core#",
        "owl": "http://www.w3.org/2002/07/owl#",
        "skos:broader": {
            "@type": "@id"
        },
        "skos:inScheme": {
            "@type": "@id"
        },
        "skos:related": {
            "@type": "@id"
        },
        "skos:narrower": {
            "@type": "@id"
        },
        "skos:hasTopConcept": {
            "@type": "@id"
        },
        "skos:topConceptOf": {
            "@type": "@id"
        }
    },
    "@id": "LT9444882",
    "@type": "skos:Concept",
    "skos:inScheme": "restitutio in integrum",
    "owl:sameAs": "https://iate.europa.eu/entry/result/833373",
    "skos:topConceptOf": "LT9444882",
    "skos:prefLabel": [
        {
            "@language": "es",
            "@value": "restitutio in integrum"
        },
        {
            "@language": "en",
            "@value": "restitutio in integrum"
        },
        {
            "@language": "de",
            "@value": "restitutio in integrum"
        },
        {
            "@language": "nl",
            "@value": "restitutio in integrum"
        }
    ],
    "skos:altLabel": [
        {
            "@language": "de",
            "@value": "Wiedereinsetzung in den vorigen Stand"
        },
        {
            "@language": "nl",
            "@value": "herstel in de vorige toestand"
        },
        {
            "@language": "de",
            "@value": ""
        }
    ],
    "skos:definition": [
        {
            "@language": "nl",
            "@value": "\"Restitutio in integrum : herstel in de vorige toestand speciaal krachtens daartoe strekkende vordering krachtens vonnis door rechterlijke tussenkomst.\""
        }
    ]
}