{
    "@context": {
        "@base": "http://lynx-project.eu/kos/",
        "dcterms": "http://purl.org/dc/terms/",
        "rdfs": "http://www.w3.org/2000/01/rdf-schema#",
        "rdf": "http://www.w3.org/1999/02/22-rdf-syntax-ns#",
        "dc": "http://purl.org/dc/elements/1.1/",
        "skos": "http://www.w3.org/2004/02/skos/core#",
        "owl": "http://www.w3.org/2002/07/owl#",
        "skos:broader": {
            "@type": "@id"
        },
        "skos:inScheme": {
            "@type": "@id"
        },
        "skos:related": {
            "@type": "@id"
        },
        "skos:narrower": {
            "@type": "@id"
        },
        "skos:hasTopConcept": {
            "@type": "@id"
        },
        "skos:topConceptOf": {
            "@type": "@id"
        }
    },
    "@id": "LT6485611",
    "@type": "skos:Concept",
    "skos:inScheme": "verwandtschaft",
    "owl:sameAs": "https://iate.europa.eu/entry/result/3583368",
    "skos:topConceptOf": "LT6485611",
    "skos:prefLabel": [
        {
            "@language": "es",
            "@value": "parentesco por consanguinidad"
        },
        {
            "@language": "en",
            "@value": "blood relationship"
        },
        {
            "@language": "de",
            "@value": "verwandtschaft"
        },
        {
            "@language": "nl",
            "@value": "bloedverwantschap"
        },
        {
            "@language": "de",
            "@value": "verwandtschaft"
        },
        {
            "@language": "de",
            "@value": "verwandtschaft"
        },
        {
            "@language": "de",
            "@value": "verwandtschaft"
        },
        {
            "@language": "nl",
            "@value": "bloedverwantschap"
        },
        {
            "@language": "es",
            "@value": "grado de parentesco"
        },
        {
            "@language": "en",
            "@value": "degree of relationship"
        },
        {
            "@language": "de",
            "@value": "verwandtschaft"
        },
        {
            "@language": "nl",
            "@value": "graad van bloedverwantschap"
        }
    ],
    "skos:altLabel": [
        {
            "@language": "en",
            "@value": "relationship by consanguinity"
        },
        {
            "@language": "de",
            "@value": "Verwandtschaft"
        },
        {
            "@language": "de",
            "@value": "verwandtschaftliche Beziehungen"
        },
        {
            "@language": "de",
            "@value": "Grad der Verwandtschaft"
        },
        {
            "@language": "nl",
            "@value": "graad van verwantschap"
        },
        {
            "@language": "de",
            "@value": ""
        }
    ],
    "skos:definition": [
        {
            "@language": "es",
            "@value": "Parentesco nacido de la generación. Relación social establecida sobre la base de descendencia de un antepasado común actual o supuesto. Puede ser lineal cuando una persona es el antepasado directo de otra o colateral cuando se da un común antepasado último sin que los individuos estén vinculados por una línea directa de descendencia. [ES]"
        },
        {
            "@language": "de",
            "@value": "Verbindung zwischen Personen von denen entweder eine von der anderen abstammt (Verwandtschaft in gerader Linie) oder beide von derselben dritten Person abstammen (Verwandtschaft in der Seitenlinie) [DE]"
        },
        {
            "@language": "nl",
            "@value": "Bloedverwantschap verbindt personen op grond van afstamming. De bloedverwantschap is de band die bestaat tussen personen die van elkaar afstammen of een gemeenschappelijke stamouder hebben. Een bloedverwant is iemand met dezelfde familie telg van het zelfde geslacht."
        },
        {
            "@language": "de",
            "@value": "auf blutmäßiger Abstammung beruhende Verbindung mehrerer Personen(also z.B.nicht Ehegatten)"
        },
        {
            "@language": "nl",
            "@value": "De afstand in bloedverwantschap wordt bepaald door het getal van de generaties; elke generatie wordt een graad genoemd. [BE] / De graad van bloedverwantschap wordt bepaald door het aantal der geboorten die de bloedverwantschap hebben veroorzaakt. Hierbij telt een erkenning een gerechtelijke vaststelling van het vaderschap of een adoptie als geboorte. [NL]"
        }
    ]
}